cursexml.py
setup.py
cursexml.egg-info/PKG-INFO
cursexml.egg-info/SOURCES.txt
cursexml.egg-info/dependency_links.txt
cursexml.egg-info/entry_points.txt
cursexml.egg-info/top_level.txt