Metadata-Version: 1.1
Name: cursexml
Version: 0.1.0
Summary: UNKNOWN
Home-page: http://github.com/trehn/cursexml
Author: Torsten Rehn
Author-email: torsten@rehn.email
License: GPLv3
Keywords: XML,viewer,syntax,pretty
Platform: UNKNOWN
Classifier: Development Status :: 3 - Alpha
Classifier: Environment :: Console :: Curses
Classifier: Intended Audience :: Developers
Classifier: Intended Audience :: System Administrators
Classifier: License :: OSI Approved :: GNU General Public License v3 (GPLv3)
Classifier: Natural Language :: English
Classifier: Operating System :: OS Independent
Classifier: Programming Language :: Python :: 3
Classifier: Topic :: Text Processing :: Markup :: XML
